calculator/__init__.py
calculator/advanced_operations.py
calculator/basic_operations.py
calculator/complex_numbers.py
calculator/logarithms.py
calculator/statistics.py
calculator/trigonometry.py
tests/__init__.py
tests/test_advanced_operations.py
tests/test_basic_operations.py
tests/test_complex_numbers.py
tests/test_logarithms.py
tests/test_statistics.py
tests/test_trigonometry.py
shervan_shahparnia_calculator_4195-0.0.6.dist-info/LICENSE
shervan_shahparnia_calculator_4195-0.0.6.dist-info/METADATA
shervan_shahparnia_calculator_4195-0.0.6.dist-info/WHEEL
shervan_shahparnia_calculator_4195-0.0.6.dist-info/top_level.txt
shervan_shahparnia_calculator_4195-0.0.6.dist-info/RECORD
